Metadata-Version: 1.1
Name: tensorflow-exercise-hx
Version: 1.0.1
Summary: tensorflow练习：鸢尾花种类预测，加州房价预测
Home-page: https://pypi.org/manage/projects/
Author: hx
Author-email: huangsayn@163.com
License: MIT
Keywords: test python package
Platform: UNKNOWN
Classifier: License :: OSI Approved :: MIT License
Classifier: Programming Language :: Python
Classifier: Intended Audience :: Developers
Classifier: Operating System :: OS Independent
